README.rst
nose_pyversion.py
setup.cfg
setup.py
Nose_PyVersion.egg-info/PKG-INFO
Nose_PyVersion.egg-info/SOURCES.txt
Nose_PyVersion.egg-info/dependency_links.txt
Nose_PyVersion.egg-info/entry_points.txt
Nose_PyVersion.egg-info/not-zip-safe
Nose_PyVersion.egg-info/requires.txt
Nose_PyVersion.egg-info/top_level.txt