Metadata-Version: 1.1
Name: Nose-PyVersion
Version: 0.1b1
Summary: Nose plugin for excluding files based on python version
Home-page: http://github.com/danielholmstrom/nose-pyversion/
Author: Daniel Holmstrom
Author-email: holmstrom.daniel@gmail.com
License: MIT
Platform: any
Classifier: Development Status :: 4 - Beta
Classifier: License :: OSI Approved :: MIT License
Classifier: Environment :: Web Environment
Classifier: Intended Audience :: Developers
Classifier: Operating System :: OS Independent
Classifier: Programming Language :: Python
Classifier: Topic :: Internet :: WWW/HTTP :: Dynamic Content
Classifier: Topic :: Software Development :: Libraries :: Python Modules
